hpmser/__init__.py
hpmser/running_worker.py
hpmser/search.py
hpmser-2.2.2.dist-info/METADATA
hpmser-2.2.2.dist-info/WHEEL
hpmser-2.2.2.dist-info/top_level.txt
hpmser-2.2.2.dist-info/RECORD
