Metadata-Version: 2.4
Name: hpmser
Version: 2.2.2
Summary: Hyper Parameters Search tool
Home-page: https://github.com/piteren/hpmser.git
Author: Piotr Niewinski
Author-email: pioniewinski@gmail.com
License: MIT
Requires-Dist: psutil
Requires-Dist: pypaq
Requires-Dist: ompr
Requires-Dist: torchness
Dynamic: author
Dynamic: author-email
Dynamic: home-page
Dynamic: license
Dynamic: requires-dist
Dynamic: summary
